{
  "id": "foundation_justice_innovation_programme_1750938056",
  "title": "Justice Innovation Programme",
  "organization": "Nuffield Foundation",
  "category": "foundations",
  "subcategory": "nuffield_foundation",
  "description": "Research and innovation to improve justice systems",
  "eligibility": {
    "career_stage": "All Stages",
    "disciplines": [
      "Education",
      "Justice",
      "Welfare"
    ],
    "requirements": [
      "Employed at eligible institution",
      "Research proposal within scope",
      "Demonstrated research capability"
    ]
  },
  "funding_details": {
    "amount": {
      "min": 50000,
      "max": 200000,
      "currency": "GBP",
      "duration_years": 2
    },
    "covers": [
      "Research costs",
      "Equipment",
      "Travel",
      "Consumables"
    ]
  },
  "application": {
    "deadline": "2024-06-30",
    "next_deadline": "2025-06-30",
    "frequency": "Annual",
    "application_url": "https://www.nuffieldfoundation.org",
    "guidelines_url": "https://www.nuffieldfoundation.org"
  },
  "key_info": {
    "priority_level": "Medium",
    "competition_level": "Competitive",
    "success_rate": "28%"
  },
  "contact": {
    "email": "info@nuffieldfoundation.org",
    "phone": ""
  },
  "tags": [
    "justice",
    "innovation",
    "social-research"
  ],
  "last_updated": "2025-06-26T12:40:56.528697",
  "scraped_from": "https://www.nuffieldfoundation.org",
  "status": "active"
}